{
    "Test": false,
    "Cholec80": {
        "F1_score": 71.82219782691485,
        "F1_score_EMA": 76.10561769890742,
        "Per_video_f1": {
            "cholec80_video41": 68.16302405250467,
            "cholec80_video43": 66.74391391487656,
            "cholec80_video44": 73.03850429117328,
            "cholec80_video45": 76.87492365422243,
            "cholec80_video46": 70.64120545700496,
            "cholec80_video47": 71.13624157333469,
            "cholec80_video48": 76.15757184528734
        },
        "Per_video_f1_EMA": {
            "cholec80_video41": 66.95801285024673,
            "cholec80_video43": 77.26725049469566,
            "cholec80_video44": 77.31422240341307,
            "cholec80_video45": 78.93447617508235,
            "cholec80_video46": 77.06689867636135,
            "cholec80_video47": 76.42078320915124,
            "cholec80_video48": 78.77768008340159
        }
    },
    "Endoscapes": {
        "mAP": 47.194624309525,
        "mAP_EMA": 51.55800850675148,
        "mAP_per_class": {
            "C0": 53.441388653538,
            "C1": 52.388862899655955,
            "C2": 35.75362137538104
        },
        "mAP_per_class_EMA": {
            "C0": 55.72424027498308,
            "C1": 54.25114816851864,
            "C2": 44.6986370767527
        }
    },
    "CholecT50": {
        "AP": {
            "AP_i": 80.74219213571934,
            "AP_v": 58.96568940382919,
            "AP_t": 41.0698238768642,
            "AP_iv": 36.051050987927525,
            "AP_it": 35.37201431100668,
            "AP_ivt": 29.33494734753582
        },
        "AP_EMA": {
            "AP_i": 85.28738982603302,
            "AP_v": 63.86823675637618,
            "AP_t": 45.4917975144449,
            "AP_iv": 41.99011704099021,
            "AP_it": 39.74445942246486,
            "AP_ivt": 33.23544136607695
        }
    }
}