{
    "Test": false,
    "Cholec80": {
        "F1_score": 69.2875983688605,
        "F1_score_EMA": 78.82933459852676,
        "Per_video_f1": {
            "cholec80_video41": 63.95544688824179,
            "cholec80_video43": 66.39329924818071,
            "cholec80_video44": 68.73220215485938,
            "cholec80_video45": 79.39251512132283,
            "cholec80_video46": 74.98443697421838,
            "cholec80_video47": 69.29194394833283,
            "cholec80_video48": 62.263344246867604
        },
        "Per_video_f1_EMA": {
            "cholec80_video41": 66.2196060010465,
            "cholec80_video43": 87.82638726922788,
            "cholec80_video44": 74.61385361734087,
            "cholec80_video45": 84.58596320671711,
            "cholec80_video46": 75.1447313983473,
            "cholec80_video47": 80.64297421864148,
            "cholec80_video48": 82.77182647836617
        }
    },
    "Endoscapes": {
        "mAP": 47.166864563610524,
        "mAP_EMA": 50.4964491399859,
        "mAP_per_class": {
            "C0": 46.26830541913673,
            "C1": 50.45122518642942,
            "C2": 44.78106308526543
        },
        "mAP_per_class_EMA": {
            "C0": 48.078271301990064,
            "C1": 54.205215405442566,
            "C2": 49.20586071252507
        }
    },
    "CholecT50": {
        "AP": {
            "AP_i": 73.37815571953503,
            "AP_v": 51.15374677816772,
            "AP_t": 35.63631446489534,
            "AP_iv": 32.278835236960724,
            "AP_it": 30.043377330579546,
            "AP_ivt": 25.155145335350518
        },
        "AP_EMA": {
            "AP_i": 83.88474277657618,
            "AP_v": 59.095854271871204,
            "AP_t": 43.74927486354512,
            "AP_iv": 41.747152342833516,
            "AP_it": 39.21237441098751,
            "AP_ivt": 34.079983869922195
        }
    }
}