{
    "Test": false,
    "Cholec80": {
        "F1_score": 66.73753748131574,
        "F1_score_EMA": 64.00734918424267,
        "Per_video_f1": {
            "cholec80_video41": 68.81606694716382,
            "cholec80_video43": 63.36926828569541,
            "cholec80_video44": 70.8160219033472,
            "cholec80_video45": 66.67037166212822,
            "cholec80_video46": 65.43165760871288,
            "cholec80_video47": 65.51012259548818,
            "cholec80_video48": 66.54925336667449
        },
        "Per_video_f1_EMA": {
            "cholec80_video41": 64.52773215507747,
            "cholec80_video43": 65.62593692727351,
            "cholec80_video44": 65.0894709906742,
            "cholec80_video45": 69.31417315716726,
            "cholec80_video46": 57.18831484946655,
            "cholec80_video47": 58.05834481994188,
            "cholec80_video48": 68.24747139009783
        }
    },
    "Endoscapes": {
        "mAP": 34.03778144279006,
        "mAP_EMA": 32.90843722784203,
        "mAP_per_class": {
            "C0": 37.05977631339627,
            "C1": 31.57695611990956,
            "C2": 33.476611895064366
        },
        "mAP_per_class_EMA": {
            "C0": 33.07100999288535,
            "C1": 29.003587594541933,
            "C2": 36.65071409609881
        }
    },
    "CholecT50": {
        "AP": {
            "AP_i": 69.21903465916365,
            "AP_v": 48.859277108344486,
            "AP_t": 31.887335978714052,
            "AP_iv": 29.67459204096738,
            "AP_it": 25.544346914821304,
            "AP_ivt": 21.960824900320524
        },
        "AP_EMA": {
            "AP_i": 73.99632348845897,
            "AP_v": 50.7485268153639,
            "AP_t": 37.08240674916432,
            "AP_iv": 31.631104338721638,
            "AP_it": 31.883256047454463,
            "AP_ivt": 27.910570834413708
        }
    }
}