{
    "Test": false,
    "Cholec80": {
        "F1_score": 59.10073399678029,
        "F1_score_EMA": 39.04402145070093,
        "Per_video_f1": {
            "cholec80_video41": 66.58077110143056,
            "cholec80_video43": 51.27933289054919,
            "cholec80_video44": 55.02841774481817,
            "cholec80_video45": 68.8275315504885,
            "cholec80_video46": 58.68296327337931,
            "cholec80_video47": 59.12681126332402,
            "cholec80_video48": 54.179310153472294
        },
        "Per_video_f1_EMA": {
            "cholec80_video41": 40.32070875718715,
            "cholec80_video43": 40.41693425896878,
            "cholec80_video44": 45.852248336355366,
            "cholec80_video45": 32.23156888631066,
            "cholec80_video46": 29.468247610383475,
            "cholec80_video47": 38.527494679193985,
            "cholec80_video48": 46.49094762650712
        }
    },
    "Endoscapes": {
        "mAP": 34.64864281097969,
        "mAP_EMA": 23.871211860561427,
        "mAP_per_class": {
            "C0": 31.81253921800975,
            "C1": 34.97752047649728,
            "C2": 37.15586873843203
        },
        "mAP_per_class_EMA": {
            "C0": 19.111910785083293,
            "C1": 21.677291147661553,
            "C2": 30.824433648939436
        }
    },
    "CholecT50": {
        "AP": {
            "AP_i": 63.537007756735875,
            "AP_v": 44.734509010238426,
            "AP_t": 34.15755054184802,
            "AP_iv": 27.51775936377948,
            "AP_it": 28.79640269244449,
            "AP_ivt": 24.532082343652917
        },
        "AP_EMA": {
            "AP_i": 39.479475405085076,
            "AP_v": 30.54688324936859,
            "AP_t": 30.190262646040978,
            "AP_iv": 17.39747948674008,
            "AP_it": 18.40563685787639,
            "AP_ivt": 14.671586532224898
        }
    }
}