{
    "Test": false,
    "Cholec80": {
        "F1_score": 63.88684863815778,
        "F1_score_EMA": 69.62988842236757,
        "Per_video_f1": {
            "cholec80_video41": 59.19259853378618,
            "cholec80_video43": 59.19149151364772,
            "cholec80_video44": 65.69576867910808,
            "cholec80_video45": 73.37983626653745,
            "cholec80_video46": 65.6174858227108,
            "cholec80_video47": 59.55493011105507,
            "cholec80_video48": 64.57582954025914
        },
        "Per_video_f1_EMA": {
            "cholec80_video41": 69.65623974202815,
            "cholec80_video43": 57.595597376190796,
            "cholec80_video44": 74.06368326265174,
            "cholec80_video45": 78.87093714204184,
            "cholec80_video46": 71.8696022920921,
            "cholec80_video47": 64.44377780291569,
            "cholec80_video48": 70.90938133865266
        }
    },
    "Endoscapes": {
        "mAP": 31.270701132546673,
        "mAP_EMA": 38.27731919325401,
        "mAP_per_class": {
            "C0": 32.21450500332305,
            "C1": 27.690813241926193,
            "C2": 33.906785152390775
        },
        "mAP_per_class_EMA": {
            "C0": 35.000115470128264,
            "C1": 33.49712462508103,
            "C2": 46.33471748455273
        }
    },
    "CholecT50": {
        "AP": {
            "AP_i": 67.35477409049177,
            "AP_v": 48.0440915732424,
            "AP_t": 32.50419587868959,
            "AP_iv": 28.596043050109177,
            "AP_it": 27.476010614668706,
            "AP_ivt": 22.913402842227136
        },
        "AP_EMA": {
            "AP_i": 79.95977114236321,
            "AP_v": 55.51557369212092,
            "AP_t": 38.37370145382163,
            "AP_iv": 36.94295501782792,
            "AP_it": 35.423644434536705,
            "AP_ivt": 30.029275193624798
        }
    }
}