{
    "Test": false,
    "Cholec80": {
        "F1_score": 78.04956340140554,
        "F1_score_EMA": 78.76196016524014,
        "Per_video_f1": {
            "cholec80_video41": 80.23836278187036,
            "cholec80_video43": 69.47415582701373,
            "cholec80_video44": 84.93548906844143,
            "cholec80_video45": 84.69588463779523,
            "cholec80_video46": 84.21989837168788,
            "cholec80_video47": 62.72483504100486,
            "cholec80_video48": 80.0583180820253
        },
        "Per_video_f1_EMA": {
            "cholec80_video41": 79.61642402676314,
            "cholec80_video43": 70.53785913117619,
            "cholec80_video44": 88.67993884720748,
            "cholec80_video45": 83.04637330708272,
            "cholec80_video46": 83.18858368084092,
            "cholec80_video47": 63.74412753897685,
            "cholec80_video48": 82.52041462463363
        }
    },
    "Endoscapes": {
        "mAP": 48.644975770425916,
        "mAP_EMA": 50.65317605194194,
        "mAP_per_class": {
            "C0": 49.19906615141944,
            "C1": 51.02433774726849,
            "C2": 45.71152341258982
        },
        "mAP_per_class_EMA": {
            "C0": 51.22495534586983,
            "C1": 52.14582740481363,
            "C2": 48.58874540514236
        }
    },
    "CholecT50": {
        "AP": {
            "AP_i": 90.91885170813804,
            "AP_v": 62.48370592356257,
            "AP_t": 43.814770546410465,
            "AP_iv": 42.03665731834213,
            "AP_it": 39.68499773255203,
            "AP_ivt": 33.1305908255014
        },
        "AP_EMA": {
            "AP_i": 92.46746254989353,
            "AP_v": 63.975235346845,
            "AP_t": 47.56775437439834,
            "AP_iv": 43.96823010635594,
            "AP_it": 45.90889158942557,
            "AP_ivt": 38.13046339412467
        }
    }
}