{
    "Test": false,
    "Cholec80": {
        "F1_score": 67.35187695873454,
        "F1_score_EMA": 3.0055503741973717,
        "Per_video_f1": {
            "cholec80_video41": 66.4200257354862,
            "cholec80_video43": 72.87466717424526,
            "cholec80_video44": 71.85538944738363,
            "cholec80_video45": 64.93440810686344,
            "cholec80_video46": 66.41362595369912,
            "cholec80_video47": 58.37970659545688,
            "cholec80_video48": 70.58531569800722
        },
        "Per_video_f1_EMA": {
            "cholec80_video41": 1.8848868447441152,
            "cholec80_video43": 2.713396652512256,
            "cholec80_video44": 3.5961534497965353,
            "cholec80_video45": 2.2705955858670723,
            "cholec80_video46": 7.147329637008896,
            "cholec80_video47": 1.243009422732925,
            "cholec80_video48": 2.1834810267198006
        }
    },
    "Endoscapes": {
        "mAP": 47.60143345062128,
        "mAP_EMA": 11.582073173610755,
        "mAP_per_class": {
            "C0": 48.78870552510407,
            "C1": 43.40991387255006,
            "C2": 50.60568095420971
        },
        "mAP_per_class_EMA": {
            "C0": 14.114207184328084,
            "C1": 9.53717983820283,
            "C2": 11.094832498301352
        }
    },
    "CholecT50": {
        "AP": {
            "AP_i": 90.17642132109516,
            "AP_v": 61.857516861318494,
            "AP_t": 48.096329653748434,
            "AP_iv": 40.25090261383036,
            "AP_it": 42.34486184960398,
            "AP_ivt": 36.281688305215454
        },
        "AP_EMA": {
            "AP_i": 22.90858900775861,
            "AP_v": 14.748895106949524,
            "AP_t": 12.61506855838813,
            "AP_iv": 8.63425928140279,
            "AP_it": 6.839389593902305,
            "AP_ivt": 5.497481323378661
        }
    }
}