{
    "Test": false,
    "Cholec80": {
        "F1_score": 74.58887449687464,
        "F1_score_EMA": 76.0513235379992,
        "Per_video_f1": {
            "cholec80_video41": 73.71046259621458,
            "cholec80_video43": 69.37665281567973,
            "cholec80_video44": 81.82197161190248,
            "cholec80_video45": 82.97175748155055,
            "cholec80_video46": 77.27317915952734,
            "cholec80_video47": 62.02545248087104,
            "cholec80_video48": 74.94264533237669
        },
        "Per_video_f1_EMA": {
            "cholec80_video41": 72.08388187332659,
            "cholec80_video43": 73.39862500101798,
            "cholec80_video44": 84.14750121427146,
            "cholec80_video45": 85.5232456288913,
            "cholec80_video46": 78.55765121668998,
            "cholec80_video47": 64.48838579846266,
            "cholec80_video48": 74.15997403333444
        }
    },
    "Endoscapes": {
        "mAP": 40.70897191468071,
        "mAP_EMA": 48.34114254840571,
        "mAP_per_class": {
            "C0": 42.29536246200289,
            "C1": 40.98228541527176,
            "C2": 38.84926786676747
        },
        "mAP_per_class_EMA": {
            "C0": 49.94490897930309,
            "C1": 49.064463944949054,
            "C2": 46.01405472096499
        }
    },
    "CholecT50": {
        "AP": {
            "AP_i": 87.31728415127641,
            "AP_v": 65.36665672409491,
            "AP_t": 45.04140298174491,
            "AP_iv": 44.4613777132434,
            "AP_it": 41.964666741940064,
            "AP_ivt": 35.9649998435713
        },
        "AP_EMA": {
            "AP_i": 91.86239439209199,
            "AP_v": 66.66093029916836,
            "AP_t": 47.767708056381665,
            "AP_iv": 44.86762183390025,
            "AP_it": 43.84403187352211,
            "AP_ivt": 37.76837523561685
        }
    }
}