{
    "Test": false,
    "Cholec80": {
        "F1_score": 59.697310337241895,
        "F1_score_EMA": 38.39160436415332,
        "Per_video_f1": {
            "cholec80_video41": 52.332937346176,
            "cholec80_video43": 53.351359555183876,
            "cholec80_video44": 60.32078909029417,
            "cholec80_video45": 65.07052854737834,
            "cholec80_video46": 63.312765694169826,
            "cholec80_video47": 62.03941573425708,
            "cholec80_video48": 61.45337639323395
        },
        "Per_video_f1_EMA": {
            "cholec80_video41": 26.84951250493449,
            "cholec80_video43": 51.48971492742104,
            "cholec80_video44": 36.74057096208468,
            "cholec80_video45": 34.518640049054426,
            "cholec80_video46": 38.75697492509458,
            "cholec80_video47": 44.399151100295605,
            "cholec80_video48": 35.98666608018841
        }
    },
    "Endoscapes": {
        "mAP": 39.21948151495854,
        "mAP_EMA": 34.82812579636363,
        "mAP_per_class": {
            "C0": 36.49926754183055,
            "C1": 41.80788771862565,
            "C2": 39.35128928441942
        },
        "mAP_per_class_EMA": {
            "C0": 34.53313588196557,
            "C1": 26.464411158158295,
            "C2": 43.48683034896702
        }
    },
    "CholecT50": {
        "AP": {
            "AP_i": 65.61109126718519,
            "AP_v": 46.31655884150465,
            "AP_t": 35.612616363428316,
            "AP_iv": 29.161919806957187,
            "AP_it": 28.391914417849886,
            "AP_ivt": 23.661990726883076
        },
        "AP_EMA": {
            "AP_i": 46.2873923733538,
            "AP_v": 31.293987445648696,
            "AP_t": 23.800643882949853,
            "AP_iv": 19.186515191614046,
            "AP_it": 16.230351517646973,
            "AP_ivt": 13.806031119701878
        }
    }
}