{
    "Test": false,
    "Cholec80": {
        "F1_score": 67.7440474824621,
        "F1_score_EMA": 72.89039461482555,
        "Per_video_f1": {
            "cholec80_video41": 64.62026014078742,
            "cholec80_video43": 70.66680159502259,
            "cholec80_video44": 66.03009173734212,
            "cholec80_video45": 73.9121427891179,
            "cholec80_video46": 67.1483838619667,
            "cholec80_video47": 61.38063428314846,
            "cholec80_video48": 70.4500179698495
        },
        "Per_video_f1_EMA": {
            "cholec80_video41": 73.81121360442042,
            "cholec80_video43": 70.4214297138642,
            "cholec80_video44": 76.8626413970084,
            "cholec80_video45": 80.38627955750354,
            "cholec80_video46": 72.65791810807275,
            "cholec80_video47": 64.81438733865684,
            "cholec80_video48": 71.2788925842527
        }
    },
    "Endoscapes": {
        "mAP": 43.868957420349055,
        "mAP_EMA": 45.83925244763092,
        "mAP_per_class": {
            "C0": 48.84687869212428,
            "C1": 44.61880402496509,
            "C2": 38.14118954395781
        },
        "mAP_per_class_EMA": {
            "C0": 45.35415103229599,
            "C1": 43.77899432109346,
            "C2": 48.38461198950332
        }
    },
    "CholecT50": {
        "AP": {
            "AP_i": 82.90770003881458,
            "AP_v": 62.390883696572054,
            "AP_t": 43.522284968848915,
            "AP_iv": 39.82813738649367,
            "AP_it": 36.11499981863598,
            "AP_ivt": 31.08131324362962
        },
        "AP_EMA": {
            "AP_i": 86.36397861584419,
            "AP_v": 62.387660272435994,
            "AP_t": 43.78506417471144,
            "AP_iv": 41.69316429399769,
            "AP_it": 39.81824300269232,
            "AP_ivt": 35.262621236180095
        }
    }
}