{
    "Test": false,
    "Cholec80": {
        "F1_score": 74.81913695861294,
        "F1_score_EMA": 78.12726747423395,
        "Per_video_f1": {
            "cholec80_video41": 75.52011332722215,
            "cholec80_video43": 69.98120379526137,
            "cholec80_video44": 80.04945840194716,
            "cholec80_video45": 81.07986674921062,
            "cholec80_video46": 77.14690549642059,
            "cholec80_video47": 60.352984395874266,
            "cholec80_video48": 79.60342654435442
        },
        "Per_video_f1_EMA": {
            "cholec80_video41": 79.35952356278652,
            "cholec80_video43": 69.85591561706909,
            "cholec80_video44": 83.96518676919487,
            "cholec80_video45": 86.23062412291411,
            "cholec80_video46": 82.83841811905351,
            "cholec80_video47": 63.27711109938215,
            "cholec80_video48": 81.36409302923741
        }
    },
    "Endoscapes": {
        "mAP": 43.212907363577806,
        "mAP_EMA": 47.77156347443702,
        "mAP_per_class": {
            "C0": 50.85303069289875,
            "C1": 41.284582999652514,
            "C2": 37.50110839818216
        },
        "mAP_per_class_EMA": {
            "C0": 53.301757420792896,
            "C1": 46.907255367504405,
            "C2": 43.10567763501376
        }
    },
    "CholecT50": {
        "AP": {
            "AP_i": 89.49685448616349,
            "AP_v": 64.20643105865038,
            "AP_t": 47.13664606785444,
            "AP_iv": 40.549665972887965,
            "AP_it": 40.10568371375733,
            "AP_ivt": 34.83147353078009
        },
        "AP_EMA": {
            "AP_i": 93.25779280521327,
            "AP_v": 65.51940791429583,
            "AP_t": 47.600609828464776,
            "AP_iv": 45.429700024091176,
            "AP_it": 47.593542330524826,
            "AP_ivt": 40.23951027020803
        }
    }
}