{
    "Test": false,
    "Cholec80": {
        "F1_score": 75.58878444144335,
        "F1_score_EMA": 77.21302675377133,
        "Per_video_f1": {
            "cholec80_video41": 71.82857228941867,
            "cholec80_video43": 72.15398796688226,
            "cholec80_video44": 82.86074114173874,
            "cholec80_video45": 79.43283202790909,
            "cholec80_video46": 80.76883361386473,
            "cholec80_video47": 65.45988558824304,
            "cholec80_video48": 76.61663846204695
        },
        "Per_video_f1_EMA": {
            "cholec80_video41": 76.5530489569045,
            "cholec80_video43": 70.22652867515986,
            "cholec80_video44": 86.31469501835983,
            "cholec80_video45": 80.93998707197406,
            "cholec80_video46": 83.16892529861596,
            "cholec80_video47": 64.27783098408048,
            "cholec80_video48": 79.01017127130461
        }
    },
    "Endoscapes": {
        "mAP": 43.1499012798619,
        "mAP_EMA": 45.462439226412975,
        "mAP_per_class": {
            "C0": 47.21660463317407,
            "C1": 43.226139923344306,
            "C2": 39.00695928306733
        },
        "mAP_per_class_EMA": {
            "C0": 44.12233504593831,
            "C1": 47.47834614167329,
            "C2": 44.78663649162733
        }
    },
    "CholecT50": {
        "AP": {
            "AP_i": 89.56871462998174,
            "AP_v": 63.891593184056184,
            "AP_t": 45.05017312499274,
            "AP_iv": 41.05530009663806,
            "AP_it": 41.42478702577644,
            "AP_ivt": 35.70814045889365
        },
        "AP_EMA": {
            "AP_i": 92.10720961845097,
            "AP_v": 67.40892071251719,
            "AP_t": 49.837070494827216,
            "AP_iv": 44.197838773497416,
            "AP_it": 46.6265930592587,
            "AP_ivt": 39.16431901807653
        }
    }
}