{
    "Test": false,
    "Cholec80": {
        "F1_score": 65.12989524071347,
        "F1_score_EMA": 8.456140578874113,
        "Per_video_f1": {
            "cholec80_video41": 66.76083524019492,
            "cholec80_video43": 54.82737402022796,
            "cholec80_video44": 70.78265316066624,
            "cholec80_video45": 74.94317819100411,
            "cholec80_video46": 66.8823596698391,
            "cholec80_video47": 59.59277137045026,
            "cholec80_video48": 62.120095032611665
        },
        "Per_video_f1_EMA": {
            "cholec80_video41": 8.776647696939115,
            "cholec80_video43": 6.189597750538732,
            "cholec80_video44": 10.134479222511477,
            "cholec80_video45": 9.104479169479122,
            "cholec80_video46": 9.426202447772763,
            "cholec80_video47": 7.68568597070461,
            "cholec80_video48": 7.875891794172965
        }
    },
    "Endoscapes": {
        "mAP": 40.67154776102561,
        "mAP_EMA": 11.142360514830493,
        "mAP_per_class": {
            "C0": 36.5466810381368,
            "C1": 39.7806958949922,
            "C2": 45.68726634994781
        },
        "mAP_per_class_EMA": {
            "C0": 12.235960100739348,
            "C1": 10.212946006438765,
            "C2": 10.978175437313368
        }
    },
    "CholecT50": {
        "AP": {
            "AP_i": 81.81750724456221,
            "AP_v": 61.569448520825176,
            "AP_t": 44.396901972988125,
            "AP_iv": 38.83603443204207,
            "AP_it": 38.17604964971856,
            "AP_ivt": 32.84622096997002
        },
        "AP_EMA": {
            "AP_i": 26.330198960255146,
            "AP_v": 17.03176462052177,
            "AP_t": 13.059697823545235,
            "AP_iv": 9.468231772891892,
            "AP_it": 6.767092002560841,
            "AP_ivt": 5.410565286773662
        }
    }
}