{
    "Test": false,
    "Cholec80": {
        "F1_score": 70.3174393654629,
        "F1_score_EMA": 66.22556147390166,
        "Per_video_f1": {
            "cholec80_video41": 69.06415383518691,
            "cholec80_video43": 61.88278713394123,
            "cholec80_video44": 78.39726533077058,
            "cholec80_video45": 72.28136334497704,
            "cholec80_video46": 74.46195518380296,
            "cholec80_video47": 63.644499193362705,
            "cholec80_video48": 72.49005153619892
        },
        "Per_video_f1_EMA": {
            "cholec80_video41": 61.4093805252004,
            "cholec80_video43": 61.78234235820066,
            "cholec80_video44": 78.36938787925709,
            "cholec80_video45": 68.4984268189286,
            "cholec80_video46": 66.37099823147821,
            "cholec80_video47": 59.89651556356799,
            "cholec80_video48": 67.25187894067871
        }
    },
    "Endoscapes": {
        "mAP": 33.970772788165455,
        "mAP_EMA": 37.967795285013416,
        "mAP_per_class": {
            "C0": 29.276679473445537,
            "C1": 33.06808844726438,
            "C2": 39.567550443786445
        },
        "mAP_per_class_EMA": {
            "C0": 34.53474367357888,
            "C1": 39.08301811912162,
            "C2": 40.28562406233975
        }
    },
    "CholecT50": {
        "AP": {
            "AP_i": 66.28179990651809,
            "AP_v": 45.69498422477618,
            "AP_t": 35.18325217257334,
            "AP_iv": 27.465531345328127,
            "AP_it": 29.670269200370782,
            "AP_ivt": 25.414277938521305
        },
        "AP_EMA": {
            "AP_i": 60.888310371624925,
            "AP_v": 42.687705906179794,
            "AP_t": 34.95264095937734,
            "AP_iv": 25.917257708827453,
            "AP_it": 27.83824877251648,
            "AP_ivt": 24.01906579970121
        }
    }
}