{
    "Test": false,
    "Cholec80": {
        "F1_score": 61.47668618194694,
        "F1_score_EMA": 8.549301028712257,
        "Per_video_f1": {
            "cholec80_video41": 61.20125420430945,
            "cholec80_video43": 60.87236029818227,
            "cholec80_video44": 58.273665010968735,
            "cholec80_video45": 64.1478350013877,
            "cholec80_video46": 62.68855232093172,
            "cholec80_video47": 57.1849673520612,
            "cholec80_video48": 65.96816908578748
        },
        "Per_video_f1_EMA": {
            "cholec80_video41": 7.574793313816672,
            "cholec80_video43": 6.070826306913997,
            "cholec80_video44": 10.579872189096347,
            "cholec80_video45": 8.282751891912401,
            "cholec80_video46": 12.37065120782339,
            "cholec80_video47": 9.76332387724793,
            "cholec80_video48": 5.202888414175066
        }
    },
    "Endoscapes": {
        "mAP": 36.273860389918546,
        "mAP_EMA": 10.949000136105191,
        "mAP_per_class": {
            "C0": 31.55119914425987,
            "C1": 36.80802838719532,
            "C2": 40.46235363830044
        },
        "mAP_per_class_EMA": {
            "C0": 11.6386010719918,
            "C1": 10.105316139296677,
            "C2": 11.103083197027093
        }
    },
    "CholecT50": {
        "AP": {
            "AP_i": 79.3361627626471,
            "AP_v": 56.91875103381703,
            "AP_t": 43.00607338148389,
            "AP_iv": 35.45317716292281,
            "AP_it": 37.4052138862022,
            "AP_ivt": 31.992434605975316
        },
        "AP_EMA": {
            "AP_i": 23.472177485820207,
            "AP_v": 15.083730185724011,
            "AP_t": 11.36611547878829,
            "AP_iv": 8.3404727876925,
            "AP_it": 5.917183730561508,
            "AP_ivt": 4.769568757605511
        }
    }
}