{
    "Test": false,
    "Cholec80": {
        "F1_score": 71.25292313826884,
        "F1_score_EMA": 72.96771051589963,
        "Per_video_f1": {
            "cholec80_video41": 68.62799907655514,
            "cholec80_video43": 70.24353000204748,
            "cholec80_video44": 79.78766205683449,
            "cholec80_video45": 70.32108598293753,
            "cholec80_video46": 74.49204396698829,
            "cholec80_video47": 62.40530669866068,
            "cholec80_video48": 72.89283418385831
        },
        "Per_video_f1_EMA": {
            "cholec80_video41": 72.51376585882808,
            "cholec80_video43": 67.3877820754305,
            "cholec80_video44": 80.11679433357521,
            "cholec80_video45": 78.01744325496844,
            "cholec80_video46": 73.31023650164829,
            "cholec80_video47": 63.731437137036096,
            "cholec80_video48": 75.6965144498108
        }
    },
    "Endoscapes": {
        "mAP": 39.61566104894266,
        "mAP_EMA": 43.73485269398018,
        "mAP_per_class": {
            "C0": 39.273249060984504,
            "C1": 45.88202802905708,
            "C2": 33.691706056786394
        },
        "mAP_per_class_EMA": {
            "C0": 47.1892651529711,
            "C1": 46.261939209497584,
            "C2": 37.75335371947185
        }
    },
    "CholecT50": {
        "AP": {
            "AP_i": 81.11044179457615,
            "AP_v": 54.37043948746776,
            "AP_t": 42.590484187251036,
            "AP_iv": 34.01101144083878,
            "AP_it": 40.35063818952099,
            "AP_ivt": 34.25313891927841
        },
        "AP_EMA": {
            "AP_i": 88.55958770073858,
            "AP_v": 61.0995881305717,
            "AP_t": 46.21373436227423,
            "AP_iv": 39.7016572627177,
            "AP_it": 43.167419313618986,
            "AP_ivt": 36.907570445493796
        }
    }
}