{
    "Test": false,
    "Cholec80": {
        "F1_score": 75.5609670458694,
        "F1_score_EMA": 77.97632699801815,
        "Per_video_f1": {
            "cholec80_video41": 76.05035684450118,
            "cholec80_video43": 66.98124095197187,
            "cholec80_video44": 83.82759651579012,
            "cholec80_video45": 79.36116700703417,
            "cholec80_video46": 82.66828245506618,
            "cholec80_video47": 61.45309966641735,
            "cholec80_video48": 78.58502588030493
        },
        "Per_video_f1_EMA": {
            "cholec80_video41": 78.01348622146578,
            "cholec80_video43": 68.56907795102927,
            "cholec80_video44": 86.17014310148059,
            "cholec80_video45": 84.21787185726603,
            "cholec80_video46": 84.18684567896389,
            "cholec80_video47": 64.37007612118082,
            "cholec80_video48": 80.30678805474064
        }
    },
    "Endoscapes": {
        "mAP": 41.438820528272714,
        "mAP_EMA": 46.48275614916368,
        "mAP_per_class": {
            "C0": 41.79140521445629,
            "C1": 38.028418496310955,
            "C2": 44.49663787405089
        },
        "mAP_per_class_EMA": {
            "C0": 50.773915405179835,
            "C1": 45.826016922296816,
            "C2": 42.84833612001437
        }
    },
    "CholecT50": {
        "AP": {
            "AP_i": 87.41817297799439,
            "AP_v": 61.50849184861936,
            "AP_t": 41.91717720226389,
            "AP_iv": 39.900239324795024,
            "AP_it": 38.637828891774426,
            "AP_ivt": 32.18074156251806
        },
        "AP_EMA": {
            "AP_i": 93.14369475835649,
            "AP_v": 68.32921479740988,
            "AP_t": 49.651390071205704,
            "AP_iv": 44.85796424121064,
            "AP_it": 45.60885880863024,
            "AP_ivt": 38.90391820357681
        }
    }
}