{
    "Test": false,
    "Cholec80": {
        "F1_score": 66.6323114750619,
        "F1_score_EMA": 66.61786032969307,
        "Per_video_f1": {
            "cholec80_video41": 67.86981033799647,
            "cholec80_video43": 57.31699456633829,
            "cholec80_video44": 74.23370652732875,
            "cholec80_video45": 66.9115599568085,
            "cholec80_video46": 71.49808639952894,
            "cholec80_video47": 59.94974799828441,
            "cholec80_video48": 68.64627453914795
        },
        "Per_video_f1_EMA": {
            "cholec80_video41": 68.79361495067708,
            "cholec80_video43": 56.23105226479785,
            "cholec80_video44": 75.24645715855502,
            "cholec80_video45": 67.9610999143694,
            "cholec80_video46": 73.36824962643095,
            "cholec80_video47": 55.17474648968326,
            "cholec80_video48": 69.54980190333796
        }
    },
    "Endoscapes": {
        "mAP": 30.554757555446503,
        "mAP_EMA": 32.966621187038946,
        "mAP_per_class": {
            "C0": 35.18520569314468,
            "C1": 29.582061360669233,
            "C2": 26.8970056125256
        },
        "mAP_per_class_EMA": {
            "C0": 34.14696364438316,
            "C1": 33.92870521438704,
            "C2": 30.82419470234663
        }
    },
    "CholecT50": {
        "AP": {
            "AP_i": 50.93387431139292,
            "AP_v": 36.24379870937968,
            "AP_t": 26.513859636143827,
            "AP_iv": 21.267645887803898,
            "AP_it": 21.74045107129549,
            "AP_ivt": 17.68431546309034
        },
        "AP_EMA": {
            "AP_i": 58.105861300144774,
            "AP_v": 42.770266340340555,
            "AP_t": 31.522206851844256,
            "AP_iv": 25.56463299113304,
            "AP_it": 26.2502009156218,
            "AP_ivt": 21.639344669102687
        }
    }
}