{
    "Test": false,
    "Cholec80": {
        "F1_score": 61.45354516737027,
        "F1_score_EMA": 72.49107851507866,
        "Per_video_f1": {
            "cholec80_video41": 66.82252715464107,
            "cholec80_video43": 52.05005513852631,
            "cholec80_video44": 61.4328890217478,
            "cholec80_video45": 69.64577722007319,
            "cholec80_video46": 60.5992564578397,
            "cholec80_video47": 58.231675494722815,
            "cholec80_video48": 61.39263568404105
        },
        "Per_video_f1_EMA": {
            "cholec80_video41": 72.52145199986492,
            "cholec80_video43": 65.42428772770087,
            "cholec80_video44": 79.90074629857047,
            "cholec80_video45": 77.27943271677816,
            "cholec80_video46": 71.8455121053519,
            "cholec80_video47": 68.04356717019753,
            "cholec80_video48": 72.42255158708673
        }
    },
    "Endoscapes": {
        "mAP": 33.96136748989214,
        "mAP_EMA": 42.42511026588234,
        "mAP_per_class": {
            "C0": 40.80493995524924,
            "C1": 38.57437533149284,
            "C2": 22.504787182934336
        },
        "mAP_per_class_EMA": {
            "C0": 43.20406783023258,
            "C1": 50.3866949065892,
            "C2": 33.68456806082523
        }
    },
    "CholecT50": {
        "AP": {
            "AP_i": 75.8065927731534,
            "AP_v": 51.69992808503728,
            "AP_t": 34.28751065654623,
            "AP_iv": 32.18511627709719,
            "AP_it": 29.85735599617309,
            "AP_ivt": 25.068207826902437
        },
        "AP_EMA": {
            "AP_i": 80.46151364519936,
            "AP_v": 57.06094511027468,
            "AP_t": 39.63871131813069,
            "AP_iv": 35.80014821721578,
            "AP_it": 33.291642609443926,
            "AP_ivt": 28.578896603882743
        }
    }
}