{
    "Test": false,
    "Cholec80": {
        "F1_score": 73.87515175589688,
        "F1_score_EMA": 73.59728102779133,
        "Per_video_f1": {
            "cholec80_video41": 71.76249764814764,
            "cholec80_video43": 73.6277246146413,
            "cholec80_video44": 78.46387806330047,
            "cholec80_video45": 71.81428183785782,
            "cholec80_video46": 80.40938424639599,
            "cholec80_video47": 63.829016812969854,
            "cholec80_video48": 77.21927906796505
        },
        "Per_video_f1_EMA": {
            "cholec80_video41": 78.35588675479093,
            "cholec80_video43": 72.53171586716451,
            "cholec80_video44": 76.5024525855354,
            "cholec80_video45": 73.22474759972779,
            "cholec80_video46": 77.7345054776837,
            "cholec80_video47": 64.12929364855813,
            "cholec80_video48": 72.70236526107887
        }
    },
    "Endoscapes": {
        "mAP": 44.97385806352676,
        "mAP_EMA": 43.1519375249065,
        "mAP_per_class": {
            "C0": 46.34396444079836,
            "C1": 44.0463545580818,
            "C2": 44.53125519170012
        },
        "mAP_per_class_EMA": {
            "C0": 42.75978560243065,
            "C1": 41.88195944583046,
            "C2": 44.814067526458395
        }
    },
    "CholecT50": {
        "AP": {
            "AP_i": 87.98448512810874,
            "AP_v": 62.5194537492374,
            "AP_t": 48.05296007280734,
            "AP_iv": 42.90378166548441,
            "AP_it": 42.83295109810663,
            "AP_ivt": 37.41686032359476
        },
        "AP_EMA": {
            "AP_i": 91.44792077623735,
            "AP_v": 64.02969301064572,
            "AP_t": 48.45828795168772,
            "AP_iv": 43.39822782392461,
            "AP_it": 47.58827198883984,
            "AP_ivt": 40.78236160796042
        }
    }
}